rift/__init__.py
rift/ast/__init__.py
rift/ast/ast.py
rift/ast/ast_patcher.py
rift/ast/bool_dict.py
rift/ast/calls.py
rift/ast/compiled_contract.py
rift/ast/int_dict.py
rift/ast/patchers/__init__.py
rift/ast/patchers/assert_patcher.py
rift/ast/patchers/assign_patcher.py
rift/ast/patchers/break_patcher.py
rift/ast/patchers/if_patcher.py
rift/ast/patchers/raise_patcher.py
rift/ast/patchers/return_patcher.py
rift/ast/patchers/unary_patcher.py
rift/ast/patchers/while_patcher.py
rift/ast/printer.py
rift/ast/ref_table.py
rift/ast/types/__init__.py
rift/ast/types/asm_method.py
rift/ast/types/block.py
rift/ast/types/condition.py
rift/ast/types/const.py
rift/ast/types/contract.py
rift/ast/types/control_flow.py
rift/ast/types/expr.py
rift/ast/types/loop.py
rift/ast/types/method.py
rift/ast/types/node.py
rift/ast/types/statement.py
rift/ast/utils.py
rift/bases/__init__.py
rift/bases/bare.py
rift/bases/util.py
rift/cli/__init__.py
rift/cli/commands/__init__.py
rift/cli/commands/build.py
rift/cli/commands/deploy.py
rift/cli/commands/init.py
rift/cli/commands/test.py
rift/cli/commands/utils.py
rift/cli/config.py
rift/cli/entry.py
rift/cli/util/__init__.py
rift/cli/util/dag.py
rift/cli/util/dir_helper.py
rift/cli/util/dir_util.py
rift/cli/util/git.py
rift/core/__init__.py
rift/core/annots.py
rift/core/condition.py
rift/core/entity.py
rift/core/factory.py
rift/core/invokable.py
rift/core/loop.py
rift/core/mark.py
rift/core/utils.py
rift/cst/__init__.py
rift/cst/cst_patcher.py
rift/cst/cst_visitor.py
rift/cst/import_visitor.py
rift/cst/int_visitor.py
rift/fift/__init__.py
rift/fift/bundled_fc.py
rift/fift/bundled_libs.py
rift/fift/contract.py
rift/fift/fift.py
rift/fift/fift_behavior.py
rift/fift/func.py
rift/fift/test_result.py
rift/fift/tvm.py
rift/fift/types/__init__.py
rift/fift/types/_fift_base.py
rift/fift/types/builder.py
rift/fift/types/bytes.py
rift/fift/types/cell.py
rift/fift/types/dict.py
rift/fift/types/factory.py
rift/fift/types/int.py
rift/fift/types/null.py
rift_framework-0.10.0.dist-info/entry_points.txt
rift_framework-0.10.0.dist-info/LICENSE
rift_framework-0.10.0.dist-info/WHEEL
rift_framework-0.10.0.dist-info/METADATA
rift_framework-0.10.0.dist-info/RECORD
