Metadata-Version: 2.1
Name: rift-framework
Version: 0.10.0
Summary: The magical Python -> TON Portal
License: MIT
Author: Amin Rezaei
Author-email: AminRezaei0x443@gmail.com
Requires-Python: >=3.10,<4.0
Classifier: License :: OSI Approved :: MIT License
Classifier: Programming Language :: Python :: 3
Classifier: Programming Language :: Python :: 3.10
Requires-Dist: PyYAML (>=6.0,<6.1)
Requires-Dist: appdirs (>=1.4.4,<1.5.0)
Requires-Dist: astpretty (>=3.0.0,<3.1.0)
Requires-Dist: click (>=8.1.3,<8.2.0)
Requires-Dist: colorful (>=0.5.4,<0.6.0)
Requires-Dist: cryptography (>=39.0.0,<40.0.0)
Requires-Dist: libcst (>=0.4.7,<0.5.0)
Requires-Dist: pynacl (>=1.5.0,<2.0.0)
Requires-Dist: rich (>=13.3.1,<14.0.0)
Requires-Dist: rift-tonlib (>=0.0.3,<0.0.4)
Requires-Dist: setuptools (>=65.6.3,<66.0.0)
Requires-Dist: tomlkit (>=0.11.4,<0.12.0)
Requires-Dist: tqdm (>=4.64.1,<5.0.0)
